bigmathlib/__init__.py
bigmathlib/big.py
bigmathlib-1.0.0.dist-info/METADATA
bigmathlib-1.0.0.dist-info/WHEEL
bigmathlib-1.0.0.dist-info/top_level.txt
bigmathlib-1.0.0.dist-info/RECORD
