Metadata-Version: 2.4
Name: bigmathlib
Version: 1.0.0
Summary: A small, easy-to-use wrapper around Python's Decimal with configurable precision and rounding.
Author: Jason
License: MIT
Project-URL: Homepage, https://github.com/jasonfoley57/bigmathlib
Project-URL: Source, https://github.com/jasonfoley57/bigmathlib
Project-URL: Issues, https://github.com/jasonfoley57/bigmathlib/issues
Requires-Python: >=3.7
Provides-Extra: dev
Requires-Dist: pytest; extra == "dev"
Requires-Dist: build; extra == "dev"
Requires-Dist: twine; extra == "dev"
